nr/__init__.py
nr/powerline/__init__.py
nr/powerline/chars.py
nr/powerline/cwd.py
nr/powerline/git.py
nr/powerline/server.py
nr/powerline/static.py
nr/powerline/text.py
nr/powerline/utils.py
nr/powerline/venv.py
nr.powerline-0.1.2.dist-info/LICENSE.txt
nr.powerline-0.1.2.dist-info/METADATA
nr.powerline-0.1.2.dist-info/WHEEL
nr.powerline-0.1.2.dist-info/entry_points.txt
nr.powerline-0.1.2.dist-info/top_level.txt
nr.powerline-0.1.2.dist-info/zip-safe
nr.powerline-0.1.2.dist-info/RECORD
