Metadata-Version: 2.1
Name: nr.powerline
Version: 0.1.2
Summary: Package description here.
Home-page: https://git.niklasrosenstein.com/NiklasRosenstein/powerline
Author: Niklas Rosenstein
Author-email: rosensteinniklas@gmail.com
License: MIT
Platform: UNKNOWN
Requires-Python: >=3.5.0,<4.0.0
Requires-Dist: nr.ansiterm (<0.1.0,>=0.0.1)
Requires-Dist: nr.databind.core (<0.1.0,>=0.0.6)
Requires-Dist: nr.databind.json (<0.1.0,>=0.0.6)
Requires-Dist: nr.interface (<0.1.0,>=0.0.2)
Requires-Dist: nr.sumtype (<0.1.0,>=0.0.3)
Requires-Dist: nr.utils.process (<0.1.0,>=0.0.3)
